{
  "log": {
    "level": "info",
    "timestamp": true
  },
  "inbounds": [
    {
      "type": "mixed",
      "tag": "mixed-in",
      "listen": "127.0.0.1",
      "listen_port": 7890
    }
  ],
  "outbounds": [
    {
      "type": "anytls",
      "tag": "anyreality-out",
      "server": "server_host",
      "server_port": 443,
      "password": "password",
      "idle_session_check_interval": "30s",
      "idle_session_timeout": "30s",
      "min_idle_session": 5,
      "tls": {
        "enabled": true,
        "server_name": "www.microsoft.com",
        "utls": {
          "enabled": true,
          "fingerprint": "chrome"
        },
        "reality": {
          "enabled": true,
          "public_key": "public_key",
          "short_id": "short_id"
        }
      }
    },
    {
      "type": "direct",
      "tag": "direct"
    },
    {
      "type": "block",
      "tag": "block"
    }
  ],
  "route": {
    "rule_set": [
      {
        "type": "local",
        "tag": "proxy-rules",
        "format": "source",
        "path": "/Users/vjf/.sing-box/rules/proxy-rules.json"
      },
      {
        "type": "local",
        "tag": "direct-rules",
        "format": "source",
        "path": "/Users/vjf/.sing-box/rules/direct-rules.json"
      }
    ],
    "rules": [
      {
        "rule_set": [
          "proxy-rules"
        ],
        "action": "route",
        "outbound": "anyreality-out"
      },
      {
        "rule_set": [
          "direct-rules"
        ],
        "action": "route",
        "outbound": "direct"
      }
    ],
    "final": "anyreality-out",
    "auto_detect_interface": true
  }
}
